kancolatex/__init__.py
kancolatex/__main__.py
kancolatex/database.py
kancolatex/logger.py
kancolatex/path.py
kancolatex/utils.py
kancolatex/data/data.db
kancolatex/data/db_create.sql
kancolatex/data/db_drop.sql
kancolatex/data/eo/query_fit_bonus_all.sql
kancolatex/data/eo/query_fit_bonus_by_equipment_id.sql
kancolatex/data/eo/query_fit_bonus_by_equipment_type.sql
kancolatex/data/kc3/query_equipment_name_en_by_key.sql
kancolatex/data/kc3/query_ship_name_en_by_key.sql
kancolatex/data/kcwiki/query_equipment_by_id.sql
kancolatex/data/kcwiki/query_equipment_by_name_japanese.sql
kancolatex/data/kcwiki/query_ship_by_id.sql
kancolatex/data/kcwiki/query_ship_by_name_japanese.sql
kancolatex/data/noro6/query_master_equipment_by_id.sql
kancolatex/data/noro6/query_master_ship_by_id.sql
kancolatex/services/noro6/common_calc.py
kancolatex/services/preprocessor/__init__.py
kancolatex/services/preprocessor/macro.py
kancolatex/services/preprocessor/process.py
kancolatex/services/translator/__init__.py
kancolatex/services/translator/translator.py
kancolatex/types/__init__.py
kancolatex/types/const.py
kancolatex/types/equipment_id.py
kancolatex/types/ship_id.py
kancolatex/types/air_control_simulator/__init__.py
kancolatex/types/air_control_simulator/serialization/__init__.py
kancolatex/types/air_control_simulator/serialization/air_control_simulator.py
kancolatex/types/deck_builder/__init__.py
kancolatex/types/deck_builder/serialization/__init__.py
kancolatex/types/deck_builder/serialization/airbase.py
kancolatex/types/deck_builder/serialization/airbase_equipment.py
kancolatex/types/deck_builder/serialization/cell.py
kancolatex/types/deck_builder/serialization/data.py
kancolatex/types/deck_builder/serialization/enemy_equipment.py
kancolatex/types/deck_builder/serialization/enemy_fleet.py
kancolatex/types/deck_builder/serialization/enemy_ship.py
kancolatex/types/deck_builder/serialization/equipment.py
kancolatex/types/deck_builder/serialization/equipment_list.py
kancolatex-0.0.7.dist-info/LICENSE
kancolatex-0.0.7.dist-info/METADATA
kancolatex-0.0.7.dist-info/WHEEL
kancolatex-0.0.7.dist-info/entry_points.txt
kancolatex-0.0.7.dist-info/top_level.txt
kancolatex-0.0.7.dist-info/RECORD
