Metadata-Version: 2.1
Name: kancolatex
Version: 0.0.7
Summary: A command line tool generate LaTex template from Kancolle Deck Builder.
License: MIT License
Requires-Python: >=3.10
License-File: LICENSE
Requires-Dist: httpx >=0.27.0
Requires-Dist: pydantic >=2.7.1
Requires-Dist: typing-extensions
Requires-Dist: python-dotenv
Provides-Extra: dev
Requires-Dist: kancolatex[test] ; extra == 'dev'
Requires-Dist: isort >=5.13.2 ; extra == 'dev'
Requires-Dist: build >=1.2.1 ; extra == 'dev'
Requires-Dist: twine >=5.1.1 ; extra == 'dev'
Provides-Extra: test
Requires-Dist: pytest ; extra == 'test'
